<?xml version='1.0' encoding='UTF-8' standalone='yes' ?>
<annotation>
  <folder>training</folder>
  <filename>Images/Tester4_robicart/images/Tester4_robicart_63.png</filename>
  <source>
    <database>synthetic initialization</database>
    <annotation>PASCAL VOC2007</annotation>
    <image>synthetic</image>
    <flickrid>none</flickrid>
  </source>
  <owner>
    <flickrid>none</flickrid>
    <name>none</name>
  </owner>
  <size>
    <width>640</width>
    <height>480</height>
    <depth>3</depth>
  </size>
  <segmented>0</segmented>
  <object>
    <boundingbox>
      <x1>311</x1>
      <y1>19</y1>
      <x2>319</x2>
      <y2>67</y2>
    </boundingbox>
  </object>
  <object>
    <boundingbox>
      <x1>319</x1>
      <y1>45</y1>
      <x2>319</x2>
      <y2>46</y2>
    </boundingbox>
  </object>
  <object>
    <boundingbox>
      <x1>7</x1>
      <y1>45</y1>
      <x2>19</x2>
      <y2>61</y2>
    </boundingbox>
  </object>
  <object>
    <boundingbox>
      <x1>0</x1>
      <y1>31</y1>
      <x2>0</x2>
      <y2>80</y2>
    </boundingbox>
  </object>
  <object>
    <boundingbox>
      <x1>0</x1>
      <y1>51</y1>
      <x2>8</x2>
      <y2>60</y2>
    </boundingbox>
  </object>
  <object>
    <boundingbox>
      <x1>0</x1>
      <y1>55</y1>
      <x2>0</x2>
      <y2>55</y2>
    </boundingbox>
  </object>
  <object>
    <boundingbox>
      <x1>236</x1>
      <y1>16</y1>
      <x2>248</x2>
      <y2>25</y2>
    </boundingbox>
  </object>
  <object>
    <boundingbox>
      <x1>247</x1>
      <y1>16</y1>
      <x2>259</x2>
      <y2>25</y2>
    </boundingbox>
  </object>
  <object>
    <boundingbox>
      <x1>231</x1>
      <y1>0</y1>
      <x2>243</x2>
      <y2>42</y2>
    </boundingbox>
  </object>
  <object>
    <boundingbox>
      <x1>220</x1>
      <y1>0</y1>
      <x2>232</x2>
      <y2>42</y2>
    </boundingbox>
  </object>
  <object>
    <boundingbox>
      <x1>244</x1>
      <y1>20</y1>
      <x2>247</x2>
      <y2>20</y2>
    </boundingbox>
  </object>
  <object>
    <boundingbox>
      <x1>235</x1>
      <y1>20</y1>
      <x2>238</x2>
      <y2>20</y2>
    </boundingbox>
  </object>
</annotation>